rst2sh5/__init__.py
rst2sh5/main.py
rst2sh5/meta.py
rst2sh5/writer.py
rst2sh5-0.0.3.dist-info/DESCRIPTION.rst
rst2sh5-0.0.3.dist-info/METADATA
rst2sh5-0.0.3.dist-info/RECORD
rst2sh5-0.0.3.dist-info/WHEEL
rst2sh5-0.0.3.dist-info/entry_points.txt
rst2sh5-0.0.3.dist-info/metadata.json
rst2sh5-0.0.3.dist-info/top_level.txt
