Metadata-Version: 2.0
Name: rst2sh5
Version: 0.0.3
Summary: Docutils writer outputting semantic HTML5
Home-page: https://github.com/sinoroc/rst2sh5
Author: sinoroc
Author-email: sinoroc.code+python@gmail.com
License: Apache-2.0
Platform: UNKNOWN
Requires-Dist: beautifulsoup4
Requires-Dist: docutils
Requires-Dist: html5lib
Requires-Dist: setuptools
Provides-Extra: package
Requires-Dist: pex; extra == 'package'
Requires-Dist: wheel; extra == 'package'
Provides-Extra: test
Requires-Dist: pytest; extra == 'test'
Requires-Dist: pytest-pep8; extra == 'test'
Requires-Dist: pytest-pylint; extra == 'test'
Requires-Dist: readme-renderer; extra == 'test'
